kw_mle/__init__.py
kw_mle/kw_mle.py
kwnpeb-0.1.11.dist-info/LICENSE
kwnpeb-0.1.11.dist-info/METADATA
kwnpeb-0.1.11.dist-info/WHEEL
kwnpeb-0.1.11.dist-info/top_level.txt
kwnpeb-0.1.11.dist-info/RECORD
