Metadata-Version: 2.1
Name: kwnpeb
Version: 0.1.11
Summary: Compute the Kiefer-Wolfowitz nonparametric maximum likelihood estimator
Home-page: https://github.com/sit836/KW_NPEB
Author: Sile Tao, Li Zhang, Guanqi Huang
Author-email: sile@ualberta.ca, lzhang2@ualberta.ca, frank.huangguanqi@gmail.com
License: UNKNOWN
Platform: UNKNOWN
Classifier: Programming Language :: Python :: 3
Classifier: License :: OSI Approved :: MIT License
Classifier: Operating System :: OS Independent
Requires-Dist: scipy (==0.19.1)
